search_helper/__init__.py
search_helper/__main__.py
search_helper/gui_commons.py
search_helper/gui_main.py
search_helper/paths.py
search_helper/data/abstract.shc.yaml
search_helper/data/debian.shc.yaml
search_helper/locale/de/LC_MESSAGES/gui_main.mo
search_helper/locale/fr/LC_MESSAGES/gui_main.mo
search_helper-1.2.3.dist-info/LICENSE
search_helper-1.2.3.dist-info/METADATA
search_helper-1.2.3.dist-info/WHEEL
search_helper-1.2.3.dist-info/entry_points.txt
search_helper-1.2.3.dist-info/top_level.txt
search_helper-1.2.3.dist-info/RECORD
