Metadata-Version: 2.1
Name: search-helper
Version: 1.2.3
Summary: Cross-platform (Tk) GUI for opening predefined search URLs in a web browser
Author-email: Rainer Schwarzbach <undisclosed@example.com>
License: Copyright (c) 2020-2023 Rainer Schwarzbach
Project-URL: Homepage, https://gitlab.com/blackstream-x/search-helper
Project-URL: Changelog, https://gitlab.com/blackstream-x/search-helper/-/blob/main/CHANGELOG.md
Project-URL: Readme, https://gitlab.com/blackstream-x/search-helper/-/blob/main/README.md
Project-URL: Documentation, https://blackstream-x.gitlab.io/search-helper
Project-URL: CI, https://gitlab.com/blackstream-x/search-helper/-/pipelines
Project-URL: Bug Tracker, https://gitlab.com/blackstream-x/search-helper/-/issues
Project-URL: Repository, https://gitlab.com/blackstream-x/search-helper.git
Keywords: gui,search,web
Classifier: Development Status :: 5 - Production/Stable
Classifier: Environment :: Win32 (MS Windows)
Classifier: Environment :: X11 Applications
Classifier: Intended Audience :: End Users/Desktop
Classifier: License :: OSI Approved :: MIT License
Classifier: Operating System :: OS Independent
Classifier: Programming Language :: Python :: 3
Classifier: Programming Language :: Python :: 3.8
Classifier: Programming Language :: Python :: 3.9
Classifier: Programming Language :: Python :: 3.10
Classifier: Programming Language :: Python :: 3.11
Classifier: Programming Language :: Python :: 3.12
Classifier: Programming Language :: Python :: 3 :: Only
Classifier: Topic :: Internet :: WWW/HTTP :: Browsers
Classifier: Topic :: Utilities
Requires-Python: >=3.8
License-File: LICENSE
Requires-Dist: serializable-trees >=0.5.1
